ml_exchange-0.3.8.dist-info/licenses/LICENSE
mlx/__init__.py
mlx/cos_backend.py
mlx/s3_kv_store.py
schema/dataset.json
schema/job.json
schema/model.json
schema/notebook.json
schema/pipeline.json
schema/pipeline_operator.json
ml_exchange-0.3.8.dist-info/METADATA
ml_exchange-0.3.8.dist-info/WHEEL
ml_exchange-0.3.8.dist-info/top_level.txt
ml_exchange-0.3.8.dist-info/RECORD
