Metadata-Version: 2.4
Name: ml-exchange
Version: 0.3.8
Summary: Machine Learning Exchange (MLX) library
Author-email: The Machine Learning Exchange Authors <terratorch@ibm.com>
License: Apache-2.0
Project-URL: Homepage, https://github.com/machine-learning-exchange/mlx
Project-URL: Source, https://github.com/machine-learning-exchange/mlx
Keywords: ml,registry,package
Classifier: Programming Language :: Python :: 3
Classifier: License :: OSI Approved :: Apache Software License
Classifier: Operating System :: OS Independent
Requires-Python: >=3.8
License-File: LICENSE
Requires-Dist: claimed
Requires-Dist: boto3
Dynamic: license-file
